{"id":53028,"path":"Assets\/_Project\/Prefabs\/ItemUI\/IconCoinPrefab.prefab","assetBundleId":-1,"components":[{"type":0,"id":55202,"data":[0.5,0.5,0.5,0.5,0.5,0.5,0,0,0,0,0,0,0,0,1,1,1,1]},{"type":5,"id":55204,"enabled":0,"class":77,"data":[0,10,0,1,0,0]}],"children":[{"id":55210,"path":"Assets\/_Project\/Prefabs\/ItemUI\/IconCoinPrefab.prefab","assetBundleId":-1,"components":[{"type":0,"id":55206,"data":[0.5,0.5,0.5,0.5,0.5,0.5,99,100,0,0,0,0,0,0,1,1,1,1]},{"type":23,"id":55252,"data":[1]},{"type":2,"id":55254,"enabled":1,"class":8,"data":[24,29732,0,0,1,4,1,1,0,0,1,1,null,null,1,1,1,1,1,0,0,0,0]}],"children":[],"data":["Icon",0,0,0,5]},{"id":55212,"path":"Assets\/_Project\/Prefabs\/ItemUI\/IconCoinPrefab.prefab","assetBundleId":-1,"components":[{"type":0,"id":55208,"data":[0.5,0.5,0.5,0.5,0.5,0.5,100,100,0,0,0,0,0,0,1,0.400000005960464,0.400000005960464,0.400000005960464]},{"type":78,"id":55238,"data":[79,48206,null,null,0,1,0,[],1]}],"children":[{"id":55256,"path":"Assets\/_Project\/Prefabs\/ItemUI\/IconCoinPrefab.prefab","assetBundleId":-1,"components":[{"type":0,"id":55214,"data":[0.5,0.5,0.5,0.5,0.5,0.5,394,407,0,0,0,0,0,0,1,1,1,1]},{"type":23,"id":55284,"data":[1]},{"type":2,"id":55286,"enabled":1,"class":8,"data":[24,55318,0,0,1,4,1,1,0,0,1,1,null,null,1,1,1,1,1,0,0,0,0]}],"children":[],"data":["Icon 1",0,1,0,5]},{"id":55262,"path":"Assets\/_Project\/Prefabs\/ItemUI\/IconCoinPrefab.prefab","assetBundleId":-1,"components":[{"type":0,"id":55216,"data":[0.5,0.5,0.5,0.5,0.5,0.5,394,407,0,0,0,0,0,0,1,1,1,1]},{"type":23,"id":55292,"data":[1]},{"type":2,"id":55294,"enabled":1,"class":8,"data":[24,55324,0,0,1,4,1,1,0,0,1,1,null,null,1,1,1,1,1,0,0,0,0]}],"children":[],"data":["Icon 2",0,0,0,5]},{"id":55260,"path":"Assets\/_Project\/Prefabs\/ItemUI\/IconCoinPrefab.prefab","assetBundleId":-1,"components":[{"type":0,"id":55218,"data":[0.5,0.5,0.5,0.5,0.5,0.5,394,407,0,0,0,0,0,0,1,1,1,1]},{"type":23,"id":55276,"data":[1]},{"type":2,"id":55278,"enabled":1,"class":8,"data":[24,55326,0,0,1,4,1,1,0,0,1,1,null,null,1,1,1,1,1,0,0,0,0]}],"children":[],"data":["Icon 3",0,0,0,5]},{"id":55240,"path":"Assets\/_Project\/Prefabs\/ItemUI\/IconCoinPrefab.prefab","assetBundleId":-1,"components":[{"type":0,"id":55220,"data":[0.5,0.5,0.5,0.5,0.5,0.5,394,407,0,0,0,0,0,0,1,1,1,1]},{"type":23,"id":55304,"data":[1]},{"type":2,"id":55306,"enabled":1,"class":8,"data":[24,55316,0,0,1,4,1,1,0,0,1,1,null,null,1,1,1,1,1,0,0,0,0]}],"children":[],"data":["Icon 4",0,0,0,5]},{"id":55264,"path":"Assets\/_Project\/Prefabs\/ItemUI\/IconCoinPrefab.prefab","assetBundleId":-1,"components":[{"type":0,"id":55222,"data":[0.5,0.5,0.5,0.5,0.5,0.5,394,407,0,0,0,0,0,0,1,1,1,1]},{"type":23,"id":55308,"data":[1]},{"type":2,"id":55310,"enabled":1,"class":8,"data":[24,55322,0,0,1,4,1,1,0,0,1,1,null,null,1,1,1,1,1,0,0,0,0]}],"children":[],"data":["Icon 5",0,0,0,5]},{"id":55250,"path":"Assets\/_Project\/Prefabs\/ItemUI\/IconCoinPrefab.prefab","assetBundleId":-1,"components":[{"type":0,"id":55224,"data":[0.5,0.5,0.5,0.5,0.5,0.5,394,407,0,0,0,0,0,0,1,1,1,1]},{"type":23,"id":55296,"data":[1]},{"type":2,"id":55298,"enabled":1,"class":8,"data":[24,55320,0,0,1,4,1,1,0,0,1,1,null,null,1,1,1,1,1,0,0,0,0]}],"children":[],"data":["Icon 6",0,0,0,5]},{"id":55244,"path":"Assets\/_Project\/Prefabs\/ItemUI\/IconCoinPrefab.prefab","assetBundleId":-1,"components":[{"type":0,"id":55226,"data":[0.5,0.5,0.5,0.5,0.5,0.5,394,407,0,0,0,0,0,0,1,-1,1,1]},{"type":23,"id":55288,"data":[1]},{"type":2,"id":55290,"enabled":1,"class":8,"data":[24,55320,0,0,1,4,1,1,0,0,1,1,null,null,1,1,1,1,1,0,0,0,0]}],"children":[],"data":["Icon 7",0,0,0,5]},{"id":55248,"path":"Assets\/_Project\/Prefabs\/ItemUI\/IconCoinPrefab.prefab","assetBundleId":-1,"components":[{"type":0,"id":55228,"data":[0.5,0.5,0.5,0.5,0.5,0.5,394,407,0,0,0,0,0,0,1,-1,1,1]},{"type":23,"id":55312,"data":[1]},{"type":2,"id":55314,"enabled":1,"class":8,"data":[24,55322,0,0,1,4,1,1,0,0,1,1,null,null,1,1,1,1,1,0,0,0,0]}],"children":[],"data":["Icon 8",0,0,0,5]},{"id":55242,"path":"Assets\/_Project\/Prefabs\/ItemUI\/IconCoinPrefab.prefab","assetBundleId":-1,"components":[{"type":0,"id":55230,"data":[0.5,0.5,0.5,0.5,0.5,0.5,394,407,0,0,0,0,0,0,1,-1,1,1]},{"type":23,"id":55300,"data":[1]},{"type":2,"id":55302,"enabled":1,"class":8,"data":[24,55316,0,0,1,4,1,1,0,0,1,1,null,null,1,1,1,1,1,0,0,0,0]}],"children":[],"data":["Icon 9",0,0,0,5]},{"id":55266,"path":"Assets\/_Project\/Prefabs\/ItemUI\/IconCoinPrefab.prefab","assetBundleId":-1,"components":[{"type":0,"id":55232,"data":[0.5,0.5,0.5,0.5,0.5,0.5,394,407,0,0,0,0,0,0,1,-1,1,1]},{"type":23,"id":55268,"data":[1]},{"type":2,"id":55270,"enabled":1,"class":8,"data":[24,55326,0,0,1,4,1,1,0,0,1,1,null,null,1,1,1,1,1,0,0,0,0]}],"children":[],"data":["Icon 10",0,0,0,5]},{"id":55258,"path":"Assets\/_Project\/Prefabs\/ItemUI\/IconCoinPrefab.prefab","assetBundleId":-1,"components":[{"type":0,"id":55234,"data":[0.5,0.5,0.5,0.5,0.5,0.5,394,407,0,0,0,0,0,0,1,-1,1,1]},{"type":23,"id":55272,"data":[1]},{"type":2,"id":55274,"enabled":1,"class":8,"data":[24,55324,0,0,1,4,1,1,0,0,1,1,null,null,1,1,1,1,1,0,0,0,0]}],"children":[],"data":["Icon 11",0,0,0,5]},{"id":55246,"path":"Assets\/_Project\/Prefabs\/ItemUI\/IconCoinPrefab.prefab","assetBundleId":-1,"components":[{"type":0,"id":55236,"data":[0.5,0.5,0.5,0.5,0.5,0.5,394,407,0,0,0,0,0,0,1,-1,1,1]},{"type":23,"id":55280,"data":[1]},{"type":2,"id":55282,"enabled":1,"class":8,"data":[24,55318,0,0,1,4,1,1,0,0,1,1,null,null,1,1,1,1,1,0,0,0,0]}],"children":[],"data":["Icon 12",0,0,0,5]}],"data":["Animator",0,1,0,5]}],"data":["IconCoinPrefab",0,1,0,5]}